csrtool/__init__.py
csrtool/cli.py
csrtool/csrutils.py
csrtool-0.0.8.dist-info/LICENSE
csrtool-0.0.8.dist-info/METADATA
csrtool-0.0.8.dist-info/WHEEL
csrtool-0.0.8.dist-info/entry_points.txt
csrtool-0.0.8.dist-info/top_level.txt
csrtool-0.0.8.dist-info/RECORD
