Metadata-Version: 2.1
Name: csrtool
Version: 0.0.8
Summary: Utility to generate CSR with DNSNames
Home-page: https://github.com/bond/csrtool
Author: Daniel Bond
Author-email: danielbondno@gmail.com
License: UNKNOWN
Platform: UNKNOWN
Classifier: Programming Language :: Python :: 3
Classifier: License :: OSI Approved :: MIT License
Classifier: Operating System :: OS Independent
Requires-Python: >=3.6
Requires-Dist: cryptography (>=36)
